MANIFEST.in
README.txt
setup.py
ProfileEye.egg-info/PKG-INFO
ProfileEye.egg-info/SOURCES.txt
ProfileEye.egg-info/dependency_links.txt
ProfileEye.egg-info/entry_points.txt
ProfileEye.egg-info/not-zip-safe
ProfileEye.egg-info/top_level.txt
profile_eye/__init__.py
profile_eye/__main__.py
profile_eye/profile_eye.py
profile_eye/_js/d3.v3.min.js
profile_eye/_js/fisheye.js
profile_eye/_js/profile_eye.js
profile_eye/_tmpl/index.html.jinja2