Metadata-Version: 1.1
Name: ProfileEye
Version: 0.1.3
Summary: A browser-based visualization frontend for gprof2dot
Home-page: UNKNOWN
Author: Ami Tavory, Qwilt
Author-email: amit@qwilt.com
License: BSD
Platform: UNKNOWN
Classifier: Development Status :: 4 - Beta
Classifier: Environment :: Console
Classifier: Intended Audience :: Developers
Classifier: License :: OSI Approved :: BSD License
Classifier: Operating System :: OS Independent
Classifier: Programming Language :: Python :: 2.7
Classifier: Programming Language :: Python :: 3
Classifier: Topic :: Software Development
Requires: setuptools
Requires: six
Requires: gprof2dot
Requires: jinja2
